c4m/__init__.py
c4m/pdk/__init__.py
c4m/pdk/freepdk45/__init__.py
c4m/pdk/freepdk45/flexlib_.py
c4m/pdk/freepdk45/freepdk45.spi
c4m/pdk/freepdk45/freepdk45_ff.spi
c4m/pdk/freepdk45/freepdk45_nom.spi
c4m/pdk/freepdk45/freepdk45_ss.spi
c4m/pdk/freepdk45/pdkmaster.py
c4m/pdk/freepdk45/pyspice.py
c4m_pdk_freepdk45-0.0.1.dist-info/LICENSE.md
c4m_pdk_freepdk45-0.0.1.dist-info/METADATA
c4m_pdk_freepdk45-0.0.1.dist-info/WHEEL
c4m_pdk_freepdk45-0.0.1.dist-info/top_level.txt
c4m_pdk_freepdk45-0.0.1.dist-info/RECORD
