Metadata-Version: 2.1
Name: c4m-pdk-freepdk45
Version: 0.0.1
Summary: example implementation of FreePDK45 as PDKMaster based PDK
Home-page: UNKNOWN
Author: Staf Verhaegen
Author-email: staf@fibraservi.eu
License: GPL-2.0-or-later OR AGPL-3.0-or-later OR CERN-OHL-S-2.0+
Project-URL: Source Code, https://gitlab.com/Chips4Makers/c4m-pdk-freepdk45
Project-URL: Bug Tracker, https://gitlab.com/Chips4Makers/c4m-pdk-freepdk45/issues
Platform: UNKNOWN
Requires-Python: ~=3.6
Requires-Dist: setuptools
Requires-Dist: c4m-PySpice (~=1.4.3.post0)
Requires-Dist: PDKMaster (~=0.1)
Requires-Dist: c4m-flexcell (~=0.0.4)
